.gitignore
00.create_env.bat
01.update_env.bat
02.remove_env.bat
README.md
documentacion.ipynb
environment.yml
hist.png
setup.py
upload.bat
config/config copy.txt
config/config.txt
config/img_readme/crisp_process.jpg
config/img_readme/install.PNG
config/macro_region/base.txt
config/macro_region/costo_sierra_selva.txt
config/macro_region/macroregionesprueba.txt
config/macro_region/prueba hugo.txt
docs/Notas_Estudiante.pptx
docs/docsPrincipal.md
docs/docdetalle/helperaccesdb/HELPER_ACCES_DB_get_juntos.md
docs/docdetalle/helperaccesdb/HELPER_ACCES_DB_get_macro_region.md
docs/docdetalle/helperaccesdb/HELPER_ACCES_DB_get_macro_regiones.md
docs/docdetalle/helperaccesdb/HELPER_ACCES_DB_get_path_BD.md
docs/docdetalle/helperaccesdb/HELPER_ACCES_DB_get_path_BD_siagie_procesado.md
docs/docdetalle/helperaccesdb/HELPER_ACCES_DB_get_path_BD_siagie_sin_procesar.md
docs/docdetalle/helperaccesdb/HELPER_ACCES_DB_get_siagie_por_anio.md
docs/docdetalle/helperaccesdb/HELPER_ACCES_DB_set_macro_region.md
docs/docdetalle/helpersiagiekpi/HELPER_SIAGIE_KPI_agregar_distancia_ini_pri.md
docs/docdetalle/helpersiagiekpi/HELPER_SIAGIE_KPI_agregar_distancia_prim_sec.md
docs/docdetalle/helpersiagiekpi/HELPER_SIAGIE_KPI_agregar_notas.md
docs/docdetalle/helpersiagiekpi/HELPER_SIAGIE_KPI_generar_kpis_agg_servicios.md
docs/docdetalle/helpersiagiekpi/HELPER_SIAGIE_KPI_generar_kpis_desercion.md
docs/docdetalle/helpersiagiekpi/HELPER_SIAGIE_KPI_generar_kpis_historicos.md
docs/docdetalle/helpersiagiekpi/HELPER_SIAGIE_KPI_generar_kpis_p_deser_by_codmod.md
docs/docdetalle/helpersiagiekpi/HELPER_SIAGIE_KPI_generar_kpis_p_deser_by_dist.md
docs/docdetalle/helpersiagiekpi/HELPER_SIAGIE_KPI_generar_kpis_traslado.md
docs/docdetalle/helpersiagiekpi/HELPER_SIAGIE_KPI_generar_kpis_traslado_a_publico.md
docs/docdetalle/helpersiagiekpi/HELPER_SIAGIE_KPI_get_coeff.md
docs/docdetalle/helpersiagiekpi/HELPER_SIAGIE_KPI_get_kpi_foraneo.md
docs/docdetalle/helperterceroskpi/HELPER_TERCEROS_KPI_agregar_ECE.md
med_data_science_helper_utility.egg-info/PKG-INFO
med_data_science_helper_utility.egg-info/SOURCES.txt
med_data_science_helper_utility.egg-info/dependency_links.txt
med_data_science_helper_utility.egg-info/entry_points.txt
med_data_science_helper_utility.egg-info/requires.txt
med_data_science_helper_utility.egg-info/top_level.txt
