Metadata-Version: 2.1
Name: med-data-science-helper-utility
Version: 0.0.69
Summary: med-data-science-helper-utility de proyectos de analitica avanzada
Download-URL: https://URL_PAQUETE/med-data-science-helper-utility/-/archive/master/med-data-science-helper-utility-master.tar
Author: Analitica Avanzada
Author-email: analitica.avanzada.talento@gmail.com
License: NOTFOUND
Keywords: med-data-science-helper-utility,paquete,package
Classifier: Development Status :: 4 - Beta
Classifier: Intended Audience :: Developers
Classifier: Topic :: Software Development :: Build Tools
Classifier: Programming Language :: Python :: 3.7
